{
  "$schema": "https://inspirebeta.net/schemas/records/hep.json",
  "_collections": ["Literature"],
  "_desy_bookkeeping": [
    { "identifier": "DA14-kp52d" },
    { "date": "2014-11-14", "expert": "M", "status": "abs" },
    { "date": "2014-11-20", "expert": "M", "status": "printed" },
    { "date": "2015-01-16", "status": "final" }
  ],
  "_private_notes": [{ "source": "CERN", "value": "CDS-1967226" }],
  "abstracts": [
    {
      "source": "arXiv",
      "value":
        "We present our results for the leading-order hadronic quark-connected contributions to the electron, the muon, and the tau anomalous magnetic moments obtained with four dynamical quarks. Performing the continuum limit and an analysis of systematic effects, full agreement with phenomenological results is found. To estimate the impact of omitting the quark-disconnected contributions to the hadronic vacuum polarisation we investigate them on one of the four-flavour ensembles. Additionally, the light quark contributions on the four-flavour sea are compared to the values obtained for $N_f=2$ physically light quarks. In the latter case different methods to fit the hadronic vacuum polarisation function are tested."
    }
  ],
  "acquisition_source": { "method": "oai", "source": "arxiv" },
  "arxiv_eprints": [{ "categories": ["hep-lat"], "value": "1411.0705" }],
  "authors": [
    {
      "affiliations": [
        {
          "record": {
            "$ref": "https://inspirebeta.net/api/institutions/902858"
          },
          "value": "Humboldt U., Berlin"
        }
      ],
      "full_name": "Burger, Florian",
      "ids": [{ "schema": "INSPIRE BAI", "value": "F.Burger.1" }],
      "raw_affiliations": [{ "value": "Humboldt U Berlin" }],
      "record": { "$ref": "https://inspirebeta.net/api/authors/1072753" },
      "signature_block": "BARGARf",
      "uuid": "257f7b59-7417-497c-b75a-293502a85c2c"
    },
    {
      "affiliations": [
        {
          "record": {
            "$ref": "https://inspirebeta.net/api/institutions/902858"
          },
          "value": "Humboldt U., Berlin"
        }
      ],
      "curated_relation": true,
      "full_name": "Hotzel, Grit",
      "ids": [{ "schema": "INSPIRE BAI", "value": "G.Hotzel.1" }],
      "raw_affiliations": [{ "value": "Humboldt University Berlin" }],
      "record": { "$ref": "https://inspirebeta.net/api/authors/1274753" },
      "signature_block": "HATSALg",
      "uuid": "781de2be-b1ef-4c04-854f-15ea1d725352"
    },
    {
      "affiliations": [
        {
          "record": {
            "$ref": "https://inspirebeta.net/api/institutions/907970"
          },
          "value": "NIC, Zeuthen"
        },
        {
          "record": {
            "$ref": "https://inspirebeta.net/api/institutions/902666"
          },
          "value": "DESY, Zeuthen"
        }
      ],
      "curated_relation": true,
      "full_name": "Jansen, Karl",
      "ids": [{ "schema": "INSPIRE BAI", "value": "K.Jansen.1" }],
      "raw_affiliations": [
        { "value": "NIC, Platanenallee 6, 15738 Zeuthen, Germany" }
      ],
      "record": { "$ref": "https://inspirebeta.net/api/authors/1004503" },
      "signature_block": "JANSANk",
      "uuid": "a0dc8dc2-d645-44f6-8b88-1bacbfa41a33"
    },
    {
      "affiliations": [
        {
          "record": {
            "$ref": "https://inspirebeta.net/api/institutions/911877"
          },
          "value": "Cyprus Inst."
        }
      ],
      "full_name": "Petschlies, Marcus",
      "ids": [{ "schema": "INSPIRE BAI", "value": "M.Petschlies.1" }],
      "raw_affiliations": [{ "value": "The Cyprus Institute" }],
      "record": { "$ref": "https://inspirebeta.net/api/authors/1052753" },
      "signature_block": "PATSLYm",
      "uuid": "ee18286d-074f-4ba9-bd1c-1185d0185072"
    }
  ],
  "citeable": true,
  "control_number": 1325985,
  "core": true,
  "curated": true,
  "document_type": ["conference paper"],
  "documents": [
    {
      "hidden": true,
      "key": "arXiv:1411.0705.pdf",
      "source": "arxiv",
      "url": "https://inspirebeta.net/files/8e8625d51bbe2d5d4ba6dc0b91bddeb2"
    }
  ],
  "dois": [{ "value": "10.22323/1.214.0145" }],
  "figures": [
    {
      "caption":
        "Chiral and continuum extrapolation of the connected leading hadronic contributions to the three lepton anomalous magnetic moments. The combined extrapolation has been performed with $a_{\\mathrm{lepton}}(m_{\\rm PS}, a) = A + B~m_{PS}^2 + C~a^2$. The dotted orange line shows $a_{\\mathrm{lepton}}(m_{\\rm PS}, 0.086\\,{\\rm fm})$, the blue line corresponds to $a_{\\mathrm{lepton}}(m_{\\rm PS}, 0.078\\,{\\rm fm})$, and the green line depicts $a_{\\mathrm{lepton}}(m_{\\rm PS}, 0.061\\,{\\rm fm})$. The inverted red triangle shows the value in the continuum limit at the physical value of the pion mass. It has been displaced to the left to facilitate the comparison with the dispersive results in the black squares for $a_{\\mathrm{e}}^{\\rm hvp}$~\\cite{Nomura:2012sb}, $a_{\\mathrm{\\mu}}^{\\mathrm{hvp}}$~\\cite{Hagiwara:2011af}, and $a_{\\mathrm{\\tau}}^{\\mathrm{hvp}}$~\\cite{Eidelman:2007sb}.",
      "filename": "all_gm2_tot.png",
      "key": "ac6f7d7149bb01ca5da6384f18ac3870",
      "source": "arxiv",
      "url": "https://inspirebeta.net/files/ac6f7d7149bb01ca5da6384f18ac3870"
    },
    {
      "caption":
        "Comparison of the light quark contributions to the unsubtracted hadronic vacuum polarisation function from quark-connected and disconnected diagrams of the local current correlator. The subscript $\\rm R$ signals that the renormalisation factor $Z_V$ is included. The values have been obtained with the analytical continuation method described in~\\cite{Feng:2013xsa} without correcting for finite-size effects.",
      "filename": "pi_loc_ren_tsum_tmax31.png",
      "key": "28a9589d3fe0f49f30712827218cc586",
      "source": "arxiv",
      "url": "https://inspirebeta.net/files/28a9589d3fe0f49f30712827218cc586"
    },
    {
      "caption":
        "Comparison of the chiral extrapolation of the light quark contributions to the three lepton anomalous magnetic moments with the values obtained with the standard definition Eq.~(\\protect\\ref{eq:amudef}) at the physical value of the pion mass (black square).",
      "filename": "all_gm2_light.png",
      "key": "8f664764881c65bf6842ee91605ee25a",
      "source": "arxiv",
      "url": "https://inspirebeta.net/files/8f664764881c65bf6842ee91605ee25a"
    }
  ],
  "imprints": [{ "date": "2014-10-31", "publisher": "SISSA" }],
  "inspire_categories": [
    { "term": "Lattice" },
    { "term": "Phenomenology-HEP" }
  ],
  "keywords": [
    { "schema": "INSPIRE", "value": "vacuum polarization: hadronic" },
    { "schema": "INSPIRE", "value": "quark: mass: twist" },
    { "schema": "INSPIRE", "value": "quark: flavor: 4" },
    { "schema": "INSPIRE", "value": "quark: flavor: 2" },
    { "schema": "INSPIRE", "value": "higher-order: 0" },
    { "schema": "INSPIRE", "value": "continuum limit" },
    { "schema": "INSPIRE", "value": "electron: magnetic moment" },
    { "schema": "INSPIRE", "value": "lepton: magnetic moment" },
    { "schema": "INSPIRE", "value": "muon: magnetic moment" },
    { "schema": "INSPIRE", "value": "quantum chromodynamics: lattice" },
    { "schema": "INSPIRE", "value": "numerical calculations" }
  ],
  "legacy_creation_date": "2014-11-05",
  "legacy_version": "20180509180950.0",
  "license": [
    {
      "imposing": "arXiv",
      "url": "http://arxiv.org/licenses/nonexclusive-distrib/1.0/"
    }
  ],
  "number_of_pages": 7,
  "preprint_date": "2014-11-03",
  "public_notes": [
    {
      "source": "arXiv",
      "value":
        "7 pages, 3 figures, Contribution to the 32nd International Symposium on Lattice Field Theory (Lattice 2014), 23-28 June 2014, Columbia University, New York, NY, USA"
    }
  ],
  "publication_info": [
    {
      "artid": "145",
      "cnum": "C14-06-23.9",
      "conference_record": {
        "$ref": "https://inspirebeta.net/api/conferences/1312308"
      },
      "journal_record": {
        "$ref": "https://inspirebeta.net/api/journals/1213080"
      },
      "journal_title": "PoS",
      "journal_volume": "LATTICE2014",
      "page_start": "145",
      "parent_record": {
        "$ref": "https://inspirebeta.net/api/literature/1373038"
      },
      "year": 2014
    }
  ],
  "references": [
    {
      "curated_relation": false,
      "record": { "$ref": "https://inspirebeta.net/api/literature/1118268" },
      "reference": {
        "arxiv_eprint": "1206.3113",
        "authors": [
          { "full_name": "Renner, D.B." },
          { "full_name": "Feng, X." },
          { "full_name": "Jansen, K." },
          { "full_name": "Petschlies, M." }
        ],
        "label": "1",
        "publication_info": {
          "artid": "022",
          "journal_title": "PoS",
          "journal_volume": "LATTICE2011",
          "page_start": "022",
          "year": 2012
        }
      }
    },
    {
      "curated_relation": false,
      "record": { "$ref": "https://inspirebeta.net/api/literature/604400" },
      "reference": {
        "arxiv_eprint": "hep-lat/0212018",
        "authors": [{ "full_name": "Blum, T." }],
        "label": "2",
        "publication_info": {
          "artid": "052001",
          "journal_title": "Phys.Rev.Lett.",
          "journal_volume": "91",
          "year": 2003
        }
      }
    },
    {
      "curated_relation": false,
      "record": { "$ref": "https://inspirebeta.net/api/literature/893768" },
      "reference": {
        "arxiv_eprint": "1103.4818",
        "authors": [
          { "full_name": "Feng, X." },
          { "full_name": "Jansen, K." },
          { "full_name": "Petschlies, M." },
          { "full_name": "Renner, D.B." }
        ],
        "label": "3",
        "publication_info": {
          "artid": "081802",
          "journal_title": "Phys.Rev.Lett.",
          "journal_volume": "107",
          "year": 2011
        }
      }
    },
    {
      "curated_relation": false,
      "record": { "$ref": "https://inspirebeta.net/api/literature/1249881" },
      "reference": {
        "arxiv_eprint": "1308.4327",
        "authors": [
          { "full_name": "Burger, F." },
          { "full_name": "Feng, X." },
          { "full_name": "Hotzel, G." },
          { "full_name": "Jansen, K." },
          { "full_name": "Petschlies, M." },
          { "full_name": "Renner, D.B." }
        ],
        "label": "4",
        "publication_info": {
          "artid": "099",
          "journal_title": "JHEP",
          "journal_volume": "02",
          "page_start": "099",
          "year": 2014
        }
      }
    },
    {
      "curated_relation": false,
      "record": { "$ref": "https://inspirebeta.net/api/literature/1128471" },
      "reference": {
        "arxiv_eprint": "1208.4194",
        "authors": [{ "full_name": "Nomura, D." }],
        "imprint": { "publisher": "Teubner" },
        "label": "5",
        "misc": ["and T"],
        "publication_info": {
          "artid": "236",
          "journal_title": "Nucl.Phys.B",
          "journal_volume": "867",
          "page_start": "236",
          "year": 2013
        }
      }
    },
    {
      "curated_relation": false,
      "record": { "$ref": "https://inspirebeta.net/api/literature/900116" },
      "reference": {
        "arxiv_eprint": "1105.3149",
        "authors": [
          { "full_name": "Hagiwara, K." },
          { "full_name": "Liao, R." },
          { "full_name": "Martin, A.D." },
          { "full_name": "Nomura, D." }
        ],
        "imprint": { "publisher": "Teubner" },
        "label": "6",
        "misc": ["and T"],
        "publication_info": {
          "artid": "085003",
          "journal_title": "J.Phys.G",
          "journal_volume": "38",
          "year": 2011
        }
      }
    },
    {
      "curated_relation": false,
      "record": { "$ref": "https://inspirebeta.net/api/literature/743557" },
      "reference": {
        "arxiv_eprint": "hep-ph/0701260",
        "authors": [
          { "full_name": "Eidelman, S." },
          { "full_name": "Passera, M." }
        ],
        "label": "7",
        "publication_info": {
          "artid": "159",
          "journal_title": "Mod.Phys.Lett.A",
          "journal_volume": "22",
          "page_start": "159",
          "year": 2007
        }
      }
    },
    {
      "curated_relation": false,
      "record": { "$ref": "https://inspirebeta.net/api/literature/1284984" },
      "reference": {
        "arxiv_eprint": "1403.1778",
        "authors": [
          { "full_name": "Chakraborty, B." },
          { "full_name": "Davies, C.T.H." },
          { "full_name": "Donald, G.C." },
          { "full_name": "Dowdall, R.J." },
          { "full_name": "Koponen, J." },
          { "full_name": "Lepage, G.P." }
        ],
        "label": "8"
      }
    },
    {
      "curated_relation": false,
      "record": { "$ref": "https://inspirebeta.net/api/literature/853397" },
      "reference": {
        "arxiv_eprint": "1004.5284",
        "authors": [
          { "full_name": "Baron, R." },
          { "full_name": "Boucaud, P." },
          { "full_name": "Carbonell, J." },
          { "full_name": "Deuzeman, A." },
          { "full_name": "Drach, V." },
          { "full_name": "Farchioni, F." }
        ],
        "label": "9",
        "publication_info": {
          "artid": "111",
          "journal_title": "JHEP",
          "journal_volume": "06",
          "page_start": "111",
          "year": 2010
        }
      }
    },
    {
      "curated_relation": false,
      "record": { "$ref": "https://inspirebeta.net/api/literature/855857" },
      "reference": {
        "arxiv_eprint": "1005.2042",
        "authors": [{ "full_name": "Baron, R." }],
        "label": "10",
        "misc": ["[European Twisted Mass Collaboration]"],
        "publication_info": {
          "artid": "299",
          "journal_title": "Comput.Phys.Commun.",
          "journal_volume": "182",
          "page_start": "299",
          "year": 2011
        }
      }
    },
    {
      "curated_relation": false,
      "record": { "$ref": "https://inspirebeta.net/api/literature/1235543" },
      "reference": {
        "arxiv_eprint": "1305.5878",
        "authors": [
          { "full_name": "Feng, X." },
          { "full_name": "Hashimoto, S." },
          { "full_name": "Hotzel, G." },
          { "full_name": "Jansen, K." },
          { "full_name": "Petschlies, M." },
          { "full_name": "Renner, D.B." }
        ],
        "label": "11",
        "publication_info": {
          "artid": "034505",
          "journal_title": "Phys.Rev.D",
          "journal_volume": "88",
          "year": 2013
        }
      }
    },
    {
      "curated_relation": false,
      "record": { "$ref": "https://inspirebeta.net/api/literature/868894" },
      "reference": {
        "arxiv_eprint": "1009.3783",
        "authors": [
          { "full_name": "Della Morte, M." },
          { "full_name": "Juttner, A." }
        ],
        "label": "12",
        "publication_info": {
          "artid": "154",
          "journal_title": "JHEP",
          "journal_volume": "11",
          "page_start": "154",
          "year": 2010
        }
      }
    },
    {
      "curated_relation": false,
      "record": { "$ref": "https://inspirebeta.net/api/literature/1264820" },
      "reference": {
        "arxiv_eprint": "1311.4522",
        "authors": [
          { "full_name": "Abdel-Rehim, A." },
          { "full_name": "Boucaud, P." },
          { "full_name": "Carrasco, N." },
          { "full_name": "Deuzeman, A." },
          { "full_name": "Dimopoulos, P." },
          { "full_name": "Frezzotti, R." }
        ],
        "label": "13",
        "publication_info": {
          "artid": "264",
          "journal_title": "PoS",
          "journal_volume": "LATTICE2013",
          "page_start": "264",
          "year": 2013
        }
      }
    },
    {
      "curated_relation": false,
      "record": { "$ref": "https://inspirebeta.net/api/literature/1114976" },
      "reference": {
        "arxiv_eprint": "1205.3695",
        "authors": [
          { "full_name": "Aubin, C." },
          { "full_name": "Blum, T." },
          { "full_name": "Golterman, M." },
          { "full_name": "Peris, S." }
        ],
        "label": "14",
        "publication_info": {
          "artid": "054509",
          "journal_title": "Phys.Rev.D",
          "journal_volume": "86",
          "year": 2012
        }
      }
    },
    {
      "curated_relation": false,
      "record": { "$ref": "https://inspirebeta.net/api/literature/1128469" },
      "reference": {
        "arxiv_eprint": "1208.4349",
        "authors": [
          { "full_name": "Blum, T." },
          { "full_name": "Izubuchi, T." },
          { "full_name": "Shintani, E." }
        ],
        "label": "15",
        "misc": ["094503"],
        "publication_info": {
          "artid": "9",
          "journal_title": "Phys.Rev.D",
          "journal_volume": "88",
          "page_start": "9",
          "year": 2013
        }
      }
    },
    {
      "curated_relation": false,
      "record": { "$ref": "https://inspirebeta.net/api/literature/1256950" },
      "reference": {
        "arxiv_eprint": "1310.1207",
        "authors": [
          { "full_name": "Michael, C." },
          { "full_name": "Ottnad, K." },
          { "full_name": "Urbach, C." }
        ],
        "label": "16",
        "misc": ["181602"],
        "publication_info": {
          "artid": "18",
          "journal_title": "Phys.Rev.Lett.",
          "journal_volume": "111",
          "page_start": "18",
          "year": 2013
        }
      }
    }
  ],
  "report_numbers": [
    { "value": "DESY-14-203" },
    { "value": "HU-EP-14-43" },
    { "value": "SFB-CPP-14-84" }
  ],
  "self": { "$ref": "https://inspirebeta.net/api/literature/1325985" },
  "texkeys": ["Burger:2014lna"],
  "titles": [
    {
      "source": "arXiv",
      "title": "Lepton anomalous magnetic moments from twisted mass fermions"
    }
  ],
  "urls": [
    {
      "description":
        "00000 Chiral and continuum extrapolation of the connected leading hadronic contributions to the three lepton anomalous magnetic moments. The combined extrapolation has been performed with $a_{\\mathrm{lepton}}(m_{\\rm PS}, a) = A + B~m_{PS}^2 + C~a^2$. The dotted orange line shows $a_{\\mathrm{lepton}}(m_{\\rm PS}, 0.086\\,{\\rm fm})$, the blue line corresponds to $a_{\\mathrm{lepton}}(m_{\\rm PS}, 0.078\\,{\\rm fm})$, and the green line depicts $a_{\\mathrm{lepton}}(m_{\\rm PS}, 0.061\\,{\\rm fm})$. The inverted red triangle shows the value in the continuum limit at the physical value of the pion mass. It has been displaced to the left to facilitate the comparison with the dispersive results in the black squares for $a_{\\mathrm{e}}^{\\rm hvp}$~\\cite{Nomura:2012sb}, $a_{\\mathrm{\\mu}}^{\\mathrm{hvp}}$~\\cite{Hagiwara:2011af}, and $a_{\\mathrm{\\tau}}^{\\mathrm{hvp}}$~\\cite{Eidelman:2007sb}.",
      "value": "http://inspirehep.net/record/1325985/files/all_gm2_tot.png"
    },
    {
      "description":
        "00002 Comparison of the chiral extrapolation of the light quark contributions to the three lepton anomalous magnetic moments with the values obtained with the standard definition Eq.~(\\protect\\ref{eq:amudef}) at the physical value of the pion mass (black square).",
      "value": "http://inspirehep.net/record/1325985/files/all_gm2_light.png"
    },
    {
      "description":
        "00001 Comparison of the light quark contributions to the unsubtracted hadronic vacuum polarisation function from quark-connected and disconnected diagrams of the local current correlator. The subscript $\\rm R$ signals that the renormalisation factor $Z_V$ is included. The values have been obtained with the analytical continuation method described in~\\cite{Feng:2013xsa} without correcting for finite-size effects.",
      "value":
        "http://inspirehep.net/record/1325985/files/pi_loc_ren_tsum_tmax31.png"
    },
    {
      "value": "http://inspirehep.net/record/1325985/files/arXiv:1411.0705.pdf"
    },
    {
      "description": "PoS server",
      "value":
        "http://pos.sissa.it/archive/conferences/214/145/LATTICE2014_145.pdf"
    }
  ]
}
